{"contents":[{"title":"","date":"1970年01月01日 00:00","tags":[],"url":"https://s.pximg.net/common/images/limit_unviewable_s.png","illust_type":"0","illust_book_style":0,"illust_page_count":1,"user_name":"","profile_img":"https://s.pximg.net/common/images/no_profile_s.png","illust_content_type":[],"illust_series":false,"illust_id":147036983,"width":100,"height":100,"user_id":25825853,"rank":1,"yes_rank":3,"rating_count":1498,"view_count":68630,"illust_upload_timestamp":-32400,"attr":"","is_masked":false,"mask_reason":"login_only"},{"title":"【会社と私生活】二人の浴衣","date":"2026年07月10日 12:00","tags":["漫画","会社と私生活","この二人の衣装を見て尊死した方にご冥福をお祈りします"],"url":"https://i.pximg.net/c/480x960/img-master/img/2026/07/10/12/00/30/147028781_p0_master1200.jpg","illust_type":"1","illust_book_style":"0","illust_page_count":"5","user_name":"金沢真之介","profile_img":"https://i.pximg.net/user-profile/img/2022/09/23/01/34/52/23368434_0daa45f98a51e102a4ef48411bffe087_50.jpg","illust_content_type":{"sexual":0,"lo":false,"grotesque":false,"violent":false,"homosexual":false,"drug":false,"thoughts":false,"antisocial":false,"religion":false,"original":true,"furry":false,"bl":false,"yuri":false},"illust_series":{"illust_series_id":"198059","illust_series_user_id":"4729811","illust_series_title":"会社と私生活-オンとオフ-","illust_series_caption":"会社と私生活でギャップのある二人が徐々に交わるお話。","illust_series_content_count":"209","illust_series_create_datetime":"2023-05-12 22:58:00","illust_series_content_illust_id":"147028781","illust_series_content_order":"209","page_url":"/user/4729811/series/198059"},"illust_id":147028781,"width":3240,"height":4050,"user_id":4729811,"rank":2,"yes_rank":2,"rating_count":1762,"view_count":81878,"illust_upload_timestamp":1783652430,"attr":"original","is_masked":false},{"title":"じいさんばあさん若返る【238】","date":"2026年07月11日 11:00","tags":["漫画","ギャンブル中毒","ざわ…ざわ…","賭博老人録コウキチ","年金賭博録カイ爺","じいさんばあさん若返る外伝","外人4コマ","三井長寿","じいさんばあさん若返る"],"url":"https://i.pximg.net/c/480x960/img-master/img/2026/07/11/11/00/03/147065583_p0_master1200.jpg","illust_type":"1","illust_book_style":"0","illust_page_count":"4","user_name":"新挑限","profile_img":"https://i.pximg.net/user-profile/img/2020/03/01/19/58/49/18022786_a68162bcd188525178444563c273baeb_50.png","illust_content_type":{"sexual":0,"lo":false,"grotesque":false,"violent":false,"homosexual":false,"drug":false,"thoughts":false,"antisocial":false,"religion":false,"original":true,"furry":false,"bl":false,"yuri":false},"illust_series":{"illust_series_id":"66844","illust_series_user_id":"14499092","illust_series_title":"じいさんばあさん若返る","illust_series_caption":"","illust_series_content_count":"244","illust_series_create_datetime":"2019-10-26 09:55:45","illust_series_content_illust_id":"147065583","illust_series_content_order":"244","page_url":"/user/14499092/series/66844"},"illust_id":147065583,"width":2428,"height":3439,"user_id":14499092,"rank":3,"yes_rank":0,"rating_count":3299,"view_count":71921,"illust_upload_timestamp":1783735203,"attr":"original","is_masked":false},{"title":"100日目 花海佑芽","date":"2026年07月10日 00:43","tags":["学園アイドルマスター","学マス","花海佑芽","100日チャレンジ","長手袋"],"url":"https://i.pximg.net/c/480x960/img-master/img/2026/07/10/00/43/46/147017299_p0_master1200.jpg","illust_type":"0","illust_book_style":"0","illust_page_count":"1","user_name":"にんげんまめ￤1日目東ア-31","profile_img":"https://i.pximg.net/user-profile/img/2024/07/28/02/31/59/26162158_514494b4a657be05485e9fb285834ac3_50.png","illust_content_type":{"sexual":0,"lo":false,"grotesque":false,"violent":false,"homosexual":false,"drug":false,"thoughts":false,"antisocial":false,"religion":false,"original":false,"furry":false,"bl":false,"yuri":false},"illust_series":false,"illust_id":147017299,"width":915,"height":1800,"user_id":38297201,"rank":4,"yes_rank":21,"rating_count":669,"view_count":20065,"illust_upload_timestamp":1783611826,"attr":"","is_masked":false},{"title":"ブルーバケーション","date":"2026年07月11日 00:00","tags":["原神","GenshinImpact","サンドローネ(原神)","コロンビーナ(原神)","原神5000users入り"],"url":"https://i.pximg.net/c/480x960/img-master/img/2026/07/11/00/00/16/147051637_p0_master1200.jpg","illust_type":"0","illust_book_style":"0","illust_page_count":"1","user_name":"torino","profile_img":"https://i.pximg.net/user-profile/img/2021/12/12/15/40/44/21877579_5514b0f68fe87b1657a32706948d624d_50.jpg","illust_content_type":{"sexual":0,"lo":false,"grotesque":false,"violent":false,"homosexual":false,"drug":false,"thoughts":false,"antisocial":false,"religion":false,"original":false,"furry":false,"bl":false,"yuri":false},"illust_series":false,"illust_id":147051637,"width":1600,"height":2955,"user_id":1960050,"rank":5,"yes_rank":0,"rating_count":5808,"view_count":39335,"illust_upload_timestamp":1783695616,"attr":"","is_masked":false},{"title":"常世","date":"2026年07月11日 00:03","tags":["オリジナル","女の子"],"url":"https://i.pximg.net/c/480x960/img-master/img/2026/07/11/00/03/32/147052101_p0_master1200.jpg","illust_type":"0","illust_book_style":"0","illust_page_count":"1","user_name":"美和野らぐ","profile_img":"https://i.pximg.net/user-profile/img/2020/01/07/22/45/59/16817311_58b403393d1b632630c28e1ddfc49885_50.png","illust_content_type":{"sexual":0,"lo":false,"grotesque":false,"violent":false,"homosexual":false,"drug":false,"thoughts":false,"antisocial":false,"religion":false,"original":true,"furry":false,"bl":false,"yuri":false},"illust_series":false,"illust_id":147052101,"width":1757,"height":1089,"user_id":7324626,"rank":6,"yes_rank":0,"rating_count":2073,"view_count":11021,"illust_upload_timestamp":1783695812,"attr":"original","is_masked":false},{"title":"チョコミント","date":"2026年07月10日 20:30","tags":["オリジナル","すいーつねこ","チョコミント","素晴らしきほっこりの世界","ネコミン党","にゃにこれかわいい","ネコミント"],"url":"https://i.pximg.net/c/480x960/img-master/img/2026/07/10/20/30/01/147041793_p0_master1200.jpg","illust_type":"0","illust_book_style":"0","illust_page_count":"1","user_name":"チャイ","profile_img":"https://i.pximg.net/user-profile/img/2021/06/19/00/51/46/20896373_a48cca187dc60808fb10161881c14199_50.png","illust_content_type":{"sexual":0,"lo":false,"grotesque":false,"violent":false,"homosexual":false,"drug":false,"thoughts":false,"antisocial":false,"religion":false,"original":true,"furry":false,"bl":false,"yuri":false},"illust_series":false,"illust_id":147041793,"width":1000,"height":1000,"user_id":1096811,"rank":7,"yes_rank":9,"rating_count":740,"view_count":11817,"illust_upload_timestamp":1783683001,"attr":"original","is_masked":false},{"title":"ラテアート","date":"2026年07月10日 03:05","tags":["女の子","バニー","OC","オリジナル"],"url":"https://i.pximg.net/c/480x960/img-master/img/2026/07/10/03/05/45/147020437_p0_master1200.jpg","illust_type":"0","illust_book_style":"0","illust_page_count":"1","user_name":"Ameもちᵕ̈*🍭","profile_img":"https://i.pximg.net/user-profile/img/2022/07/10/14/58/10/23002643_2ea7d542f9fce163e4d52b4c37646bc9_50.jpg","illust_content_type":{"sexual":0,"lo":false,"grotesque":false,"violent":false,"homosexual":false,"drug":false,"thoughts":false,"antisocial":false,"religion":false,"original":false,"furry":false,"bl":false,"yuri":false},"illust_series":false,"illust_id":147020437,"width":2894,"height":4093,"user_id":59688623,"rank":8,"yes_rank":10,"rating_count":321,"view_count":8244,"illust_upload_timestamp":1783620345,"attr":"","is_masked":false},{"title":"小話まとめ『夏』","date":"2026年07月10日 22:32","tags":["漫画","オリジナル","創作漫画","怪異さんと俺","オカルト","やさしい世界","怪異たらし","ネコと和解せよ","Gと和解せよ"],"url":"https://i.pximg.net/c/480x960/img-master/img/2026/07/10/22/32/07/147047647_p0_master1200.jpg","illust_type":"1","illust_book_style":"0","illust_page_count":"9","user_name":"ふに・無9","profile_img":"https://i.pximg.net/user-profile/img/2021/08/21/21/01/59/21268845_2b1e0be8957cfaee1c2b145ec8c8fea3_50.png","illust_content_type":{"sexual":0,"lo":false,"grotesque":false,"violent":false,"homosexual":false,"drug":false,"thoughts":false,"antisocial":false,"religion":false,"original":true,"furry":false,"bl":false,"yuri":false},"illust_series":{"illust_series_id":"284534","illust_series_user_id":"24367326","illust_series_title":"怪異さんと俺＿小話集","illust_series_caption":"","illust_series_content_count":"7","illust_series_create_datetime":"2025-05-11 18:41:21","illust_series_content_illust_id":"147047647","illust_series_content_order":"7","page_url":"/user/24367326/series/284534"},"illust_id":147047647,"width":910,"height":1276,"user_id":24367326,"rank":9,"yes_rank":13,"rating_count":1592,"view_count":39647,"illust_upload_timestamp":1783690327,"attr":"original","is_masked":false},{"title":"制服黒髪少女","date":"2026年07月10日 00:05","tags":["オリジナル","OC","黒髪","少女","制服","創作","女の子","ロングヘアー","オリジナル500users入り"],"url":"https://i.pximg.net/c/480x960/img-master/img/2026/07/10/00/05/14/147015682_p0_master1200.jpg","illust_type":"0","illust_book_style":"0","illust_page_count":"1","user_name":"CORE","profile_img":"https://i.pximg.net/user-profile/img/2014/06/08/21/12/00/7969430_f567285b2bfdd405bb0691d73e8624c0_50.jpg","illust_content_type":{"sexual":0,"lo":false,"grotesque":false,"violent":false,"homosexual":false,"drug":false,"thoughts":false,"antisocial":false,"religion":false,"original":true,"furry":false,"bl":false,"yuri":false},"illust_series":false,"illust_id":147015682,"width":1063,"height":1376,"user_id":11211325,"rank":10,"yes_rank":14,"rating_count":190,"view_count":4664,"illust_upload_timestamp":1783609514,"attr":"original","is_masked":false},{"title":"マンダロリアンまとめ","date":"2026年07月11日 13:43","tags":["マンダロリアン","エンボ","スターウォーズ","グローグー","我道(おひさ)","STARWARS1000users入り","我らの餅"],"url":"https://i.pximg.net/c/480x960/img-master/img/2026/07/11/13/43/39/147069717_p0_master1200.jpg","illust_type":"1","illust_book_style":"0","illust_page_count":"24","user_name":"案山子","profile_img":"https://i.pximg.net/user-profile/img/2018/04/17/01/33/37/14105155_b9a29168f63685211afd69fdf2c8287d_50.png","illust_content_type":{"sexual":0,"lo":false,"grotesque":false,"violent":false,"homosexual":false,"drug":false,"thoughts":false,"antisocial":false,"religion":false,"original":false,"furry":false,"bl":false,"yuri":false},"illust_series":false,"illust_id":147069717,"width":1400,"height":1800,"user_id":16897657,"rank":11,"yes_rank":0,"rating_count":1480,"view_count":20970,"illust_upload_timestamp":1783745019,"attr":"","is_masked":false},{"title":"七夕間に合った","date":"2026年07月10日 22:32","tags":["うごイラ","からめる","七夕は七月七日です","七夕","間に合ってないが","一部地域は8月7日が七夕","期限は守りましょう","ツッコミが追いつかない"],"url":"https://i.pximg.net/c/480x960/img-master/img/2026/07/10/22/32/34/147047680_master1200.jpg","illust_type":"2","illust_book_style":"0","illust_page_count":"1","user_name":"からめる","profile_img":"https://i.pximg.net/user-profile/img/2018/01/18/23/51/53/13710416_e58295f753bd436453e276be9b36ef86_50.png","illust_content_type":{"sexual":0,"lo":false,"grotesque":false,"violent":false,"homosexual":false,"drug":false,"thoughts":false,"antisocial":false,"religion":false,"original":true,"furry":false,"bl":false,"yuri":false},"illust_series":false,"illust_id":147047680,"width":700,"height":394,"user_id":6382123,"rank":12,"yes_rank":22,"rating_count":857,"view_count":12533,"illust_upload_timestamp":1783690354,"attr":"original","is_masked":true},{"title":"陰キャ男の娘ユーレイ♂と恋するハロウィン 【おとつく再掲100】","date":"2026年07月10日 12:02","tags":["漫画","恋する(おとめ)の作り方","男の娘","女装","オリジナル","創作","恋愛","こんな可愛い子が女の子のはずがない"],"url":"https://i.pximg.net/c/480x960/img-master/img/2026/07/10/12/02/13/147028906_p0_master1200.jpg","illust_type":"1","illust_book_style":"0","illust_page_count":"23","user_name":"az./万丈梓","profile_img":"https://i.pximg.net/user-profile/img/2022/06/21/03/30/40/22909679_302ab939b8d296bc1cbba2755a1788fa_50.png","illust_content_type":{"sexual":0,"lo":false,"grotesque":false,"violent":false,"homosexual":false,"drug":false,"thoughts":false,"antisocial":false,"religion":false,"original":true,"furry":false,"bl":false,"yuri":false},"illust_series":{"illust_series_id":"70545","illust_series_user_id":"5279612","illust_series_title":"恋する(おとめ)の作り方【幼馴染（♂）を女の子にしてしまった話】","illust_series_caption":"コスメ好き男子が冴えない幼馴染(♂)を男の娘にしちゃうラブコメ\r\npixivコミックで先行連載中\r\n単行本は現在⑤巻まで発売中です！","illust_series_content_count":"145","illust_series_create_datetime":"2020-01-01 16:29:54","illust_series_content_illust_id":"147028906","illust_series_content_order":"145","page_url":"/user/5279612/series/70545"},"illust_id":147028906,"width":2000,"height":2481,"user_id":5279612,"rank":13,"yes_rank":24,"rating_count":313,"view_count":19434,"illust_upload_timestamp":1783652533,"attr":"original","is_masked":false},{"title":"一纸信笺遥眷。","date":"2026年07月10日 13:50","tags":["鸣潮","秧秧玄翎","鳴潮1000users入り"],"url":"https://i.pximg.net/c/480x960/img-master/img/2026/07/10/13/50/32/147030949_p0_master1200.jpg","illust_type":"0","illust_book_style":"0","illust_page_count":"1","user_name":"Rafa","profile_img":"https://i.pximg.net/user-profile/img/2018/11/01/20/41/19/14967601_fca4f60cec5ad5dadcd3b183ed6c29fb_50.jpg","illust_content_type":{"sexual":0,"lo":false,"grotesque":false,"violent":false,"homosexual":false,"drug":false,"thoughts":false,"antisocial":false,"religion":false,"original":false,"furry":false,"bl":false,"yuri":false},"illust_series":false,"illust_id":147030949,"width":6000,"height":3133,"user_id":3970196,"rank":14,"yes_rank":29,"rating_count":551,"view_count":7561,"illust_upload_timestamp":1783659032,"attr":"","is_masked":false},{"title":"穗穗","date":"2026年07月10日 18:00","tags":["WutheringWaves","鳴潮","鸣潮","穗穗","Suisui","穂穂","ぱんつ"],"url":"https://i.pximg.net/c/480x960/img-master/img/2026/07/10/18/00/13/147036105_p0_master1200.jpg","illust_type":"0","illust_book_style":"0","illust_page_count":"2","user_name":"儒宅 Ruzhai","profile_img":"https://i.pximg.net/user-profile/img/2025/10/12/03/13/00/28005996_212c9ceb73886cfcdb8a8ac461765761_50.jpg","illust_content_type":{"sexual":1,"lo":false,"grotesque":false,"violent":false,"homosexual":false,"drug":false,"thoughts":false,"antisocial":false,"religion":false,"original":false,"furry":false,"bl":false,"yuri":false},"illust_series":false,"illust_id":147036105,"width":900,"height":1266,"user_id":12539859,"rank":15,"yes_rank":47,"rating_count":2007,"view_count":28813,"illust_upload_timestamp":1783674013,"attr":"","is_masked":true},{"title":"夏でも寒がりな年齢を詐称してるVtuberの友人Vtuber","date":"2026年07月10日 21:14","tags":["漫画","バーチャルYouTuber","VTuber","星空バアド","垣原メイス","もつガキ","おばあちゃん子","出し遅れ","示威行動"],"url":"https://i.pximg.net/c/480x960/img-master/img/2026/07/10/21/14/12/147043913_p0_master1200.jpg","illust_type":"1","illust_book_style":"0","illust_page_count":"1","user_name":"なまず　バアド四発売中！","profile_img":"https://i.pximg.net/user-profile/img/2016/03/05/16/04/25/10623809_60844afa68844eb6689f471f7f425758_50.jpg","illust_content_type":{"sexual":0,"lo":false,"grotesque":false,"violent":false,"homosexual":false,"drug":false,"thoughts":false,"antisocial":false,"religion":false,"original":true,"furry":false,"bl":false,"yuri":false},"illust_series":{"illust_series_id":"235147","illust_series_user_id":"6097232","illust_series_title":"あきらかに年齢を詐称してるVtuber","illust_series_caption":"あきらかに年齢を詐称してるVtuber・星空バアドと愉快なコメント達のシリーズです","illust_series_content_count":"859","illust_series_create_datetime":"2024-04-06 14:13:45","illust_series_content_illust_id":"147043913","illust_series_content_order":"857","page_url":"/user/6097232/series/235147"},"illust_id":147043913,"width":1573,"height":2298,"user_id":6097232,"rank":16,"yes_rank":43,"rating_count":706,"view_count":39101,"illust_upload_timestamp":1783685652,"attr":"original","is_masked":false},{"title":"蜜桃冰","date":"2026年07月10日 20:21","tags":["女の子","少女","鸣潮","千咲","泳装","千咲・白桃パフェ"],"url":"https://i.pximg.net/c/480x960/img-master/img/2026/07/10/20/21/38/147041502_p0_master1200.jpg","illust_type":"0","illust_book_style":"0","illust_page_count":"1","user_name":"千千結","profile_img":"https://i.pximg.net/user-profile/img/2020/05/04/23/42/18/18479101_c877e9d66dfe981521bce9f70c73505e_50.jpg","illust_content_type":{"sexual":0,"lo":false,"grotesque":false,"violent":false,"homosexual":false,"drug":false,"thoughts":false,"antisocial":false,"religion":false,"original":false,"furry":false,"bl":false,"yuri":false},"illust_series":false,"illust_id":147041502,"width":4214,"height":1975,"user_id":13829843,"rank":17,"yes_rank":57,"rating_count":793,"view_count":5824,"illust_upload_timestamp":1783682498,"attr":"","is_masked":false},{"title":"フリーナ","date":"2026年07月10日 00:15","tags":["女の子","少女","原神","GenshinImpact","フリーナ","フリーナ(原神)","ふつくしい"],"url":"https://i.pximg.net/c/480x960/img-master/img/2026/07/10/00/15/18/147016192_p0_master1200.jpg","illust_type":"0","illust_book_style":"0","illust_page_count":"1","user_name":"HAYUN","profile_img":"https://i.pximg.net/user-profile/img/2025/03/20/12/20/08/27123453_85dd8fe1585061e012209e914d5f4bc3_50.png","illust_content_type":{"sexual":0,"lo":false,"grotesque":false,"violent":false,"homosexual":false,"drug":false,"thoughts":false,"antisocial":false,"religion":false,"original":false,"furry":false,"bl":false,"yuri":false},"illust_series":false,"illust_id":147016192,"width":1374,"height":2300,"user_id":4222454,"rank":18,"yes_rank":102,"rating_count":130,"view_count":2465,"illust_upload_timestamp":1783610118,"attr":"","is_masked":false},{"title":"秧秧玄翎","date":"2026年07月10日 18:53","tags":["插画","绘画","女の子","WutheringWave","鸣潮","秧秧・玄翎","秧秧"],"url":"https://i.pximg.net/c/480x960/img-master/img/2026/07/10/18/53/51/147037912_p0_master1200.jpg","illust_type":"0","illust_book_style":"0","illust_page_count":"1","user_name":"晕欧欧","profile_img":"https://i.pximg.net/user-profile/img/2026/04/30/12/27/31/28812580_5034e79efc58bfd65577c2495f2c45f8_50.jpg","illust_content_type":{"sexual":0,"lo":false,"grotesque":false,"violent":false,"homosexual":false,"drug":false,"thoughts":false,"antisocial":false,"religion":false,"original":false,"furry":false,"bl":false,"yuri":false},"illust_series":false,"illust_id":147037912,"width":4254,"height":2728,"user_id":5669330,"rank":19,"yes_rank":56,"rating_count":514,"view_count":4320,"illust_upload_timestamp":1783677231,"attr":"","is_masked":false},{"title":"【会社と私生活】保のオフ","date":"2026年07月11日 12:00","tags":["漫画","会社と私生活"],"url":"https://i.pximg.net/c/480x960/img-master/img/2026/07/11/12/00/12/147066983_p0_master1200.jpg","illust_type":"1","illust_book_style":"0","illust_page_count":"2","user_name":"金沢真之介","profile_img":"https://i.pximg.net/user-profile/img/2022/09/23/01/34/52/23368434_0daa45f98a51e102a4ef48411bffe087_50.jpg","illust_content_type":{"sexual":0,"lo":false,"grotesque":false,"violent":false,"homosexual":false,"drug":false,"thoughts":false,"antisocial":false,"religion":false,"original":true,"furry":false,"bl":false,"yuri":false},"illust_series":{"illust_series_id":"225967","illust_series_user_id":"4729811","illust_series_title":"会社と私生活:オフショット","illust_series_caption":"会社と私生活の\r\nオフショットです。","illust_series_content_count":"107","illust_series_create_datetime":"2024-01-22 18:00:03","illust_series_content_illust_id":"147066983","illust_series_content_order":"106","page_url":"/user/4729811/series/225967"},"illust_id":147066983,"width":3035,"height":4299,"user_id":4729811,"rank":20,"yes_rank":0,"rating_count":833,"view_count":18842,"illust_upload_timestamp":1783738812,"attr":"original","is_masked":false},{"title":"アズライールとぐだ子とグレイちゃん","date":"2026年07月10日 15:59","tags":["Fate/GrandOrder","グレイ・リリィ","ぐだ子","蒼きアズライール"],"url":"https://i.pximg.net/c/480x960/img-master/img/2026/07/10/15/59/25/147033208_p0_master1200.jpg","illust_type":"0","illust_book_style":"0","illust_page_count":"1","user_name":"はなつるヲ/skeb募集中","profile_img":"https://i.pximg.net/user-profile/img/2022/01/07/17/02/26/22011778_cebc3a11ba6aacd7e6f8f1640d050de6_50.jpg","illust_content_type":{"sexual":0,"lo":false,"grotesque":false,"violent":false,"homosexual":false,"drug":false,"thoughts":false,"antisocial":false,"religion":false,"original":false,"furry":false,"bl":false,"yuri":false},"illust_series":false,"illust_id":147033208,"width":1996,"height":2303,"user_id":32266299,"rank":21,"yes_rank":46,"rating_count":200,"view_count":5869,"illust_upload_timestamp":1783666765,"attr":"","is_masked":false},{"title":"【短編漫画】みなしごの長い夜","date":"2026年07月10日 17:17","tags":["漫画","オリジナル漫画","おぞましあわせつない"],"url":"https://i.pximg.net/c/480x960/img-master/img/2026/07/10/17/17/32/147034977_p0_master1200.jpg","illust_type":"1","illust_book_style":"0","illust_page_count":"75","user_name":"フィビ鳥","profile_img":"https://i.pximg.net/user-profile/img/2008/12/20/23/06/04/435953_32931ec4161fd3cbbf8cfe2d66ff9152_50.jpg","illust_content_type":{"sexual":0,"lo":false,"grotesque":false,"violent":false,"homosexual":false,"drug":false,"thoughts":false,"antisocial":false,"religion":false,"original":true,"furry":false,"bl":false,"yuri":false},"illust_series":{"illust_series_id":"1719","illust_series_user_id":"104637","illust_series_title":"短編漫画","illust_series_caption":"","illust_series_content_count":"9","illust_series_create_datetime":"2017-06-21 17:56:43","illust_series_content_illust_id":"147034977","illust_series_content_order":"9","page_url":"/user/104637/series/1719"},"illust_id":147034977,"width":680,"height":1042,"user_id":104637,"rank":22,"yes_rank":33,"rating_count":1238,"view_count":19889,"illust_upload_timestamp":1783671452,"attr":"original","is_masked":false},{"title":"うすチュウと言葉","date":"2026年07月10日 00:00","tags":["漫画","ポケモン","ぽこあポケモン","うすチュウ","経験者は語る","金言","タフすぎるうすチュウシリーズ","名言","優しさの塊","かっこかわいい"],"url":"https://i.pximg.net/c/480x960/img-master/img/2026/07/10/00/00/20/147015124_p0_master1200.jpg","illust_type":"1","illust_book_style":"0","illust_page_count":"1","user_name":"iPad Pro買ったR君","profile_img":"https://s.pximg.net/common/images/no_profile_s.png","illust_content_type":{"sexual":0,"lo":false,"grotesque":false,"violent":false,"homosexual":false,"drug":false,"thoughts":false,"antisocial":false,"religion":false,"original":false,"furry":false,"bl":false,"yuri":false},"illust_series":{"illust_series_id":"309767","illust_series_user_id":"75709706","illust_series_title":"ポケモン関係","illust_series_caption":"ポケモン関係","illust_series_content_count":"193","illust_series_create_datetime":"2025-11-03 11:59:36","illust_series_content_illust_id":"147015124","illust_series_content_order":"191","page_url":"/user/75709706/series/309767"},"illust_id":147015124,"width":4961,"height":7016,"user_id":75709706,"rank":23,"yes_rank":35,"rating_count":148,"view_count":32124,"illust_upload_timestamp":1783609220,"attr":"","is_masked":false},{"title":"夏が始まった合図がした！","date":"2026年07月10日 20:23","tags":["夏","風景","背景","イラスト","オリジナル","創作","空","青空","illustration","空の鯨"],"url":"https://i.pximg.net/c/480x960/img-master/img/2026/07/10/20/23/56/147041575_p0_master1200.jpg","illust_type":"0","illust_book_style":"0","illust_page_count":"1","user_name":"まころん夏コミC48土お52日","profile_img":"https://i.pximg.net/user-profile/img/2022/07/29/00/09/46/23097459_26714df7c257cf149e2f3fdf8d7661a4_50.jpg","illust_content_type":{"sexual":0,"lo":false,"grotesque":false,"violent":false,"homosexual":false,"drug":false,"thoughts":false,"antisocial":false,"religion":false,"original":true,"furry":false,"bl":false,"yuri":false},"illust_series":false,"illust_id":147041575,"width":3096,"height":5606,"user_id":54390221,"rank":24,"yes_rank":60,"rating_count":232,"view_count":2190,"illust_upload_timestamp":1783682636,"attr":"original","is_masked":false},{"title":"グルタミン酸革命令嬢","date":"2026年07月11日 18:03","tags":["漫画","塩こんぶ","塩こん部長","異世界転生","グルタミン酸","先生何やってんすか","塩昆布","公式が最大手"],"url":"https://i.pximg.net/c/480x960/img-master/img/2026/07/11/18/03/32/147077108_p0_master1200.jpg","illust_type":"1","illust_book_style":"0","illust_page_count":"1","user_name":"上山道郎","profile_img":"https://i.pximg.net/user-profile/img/2020/10/03/21/21/47/19454684_9da8c732678d6e2dc29ba6e73cf98876_50.jpg","illust_content_type":{"sexual":0,"lo":false,"grotesque":false,"violent":false,"homosexual":false,"drug":false,"thoughts":false,"antisocial":false,"religion":false,"original":false,"furry":false,"bl":false,"yuri":false},"illust_series":false,"illust_id":147077108,"width":1500,"height":2100,"user_id":53823,"rank":25,"yes_rank":0,"rating_count":958,"view_count":17301,"illust_upload_timestamp":1783760612,"attr":"","is_masked":false},{"title":"君の星河よ","date":"2026年07月10日 00:02","tags":["VOCALOID","初音ミク","マジカルミライ2025"],"url":"https://i.pximg.net/c/480x960/img-master/img/2026/07/10/00/02/05/147015426_p0_master1200.jpg","illust_type":"0","illust_book_style":"0","illust_page_count":"1","user_name":"甘木花","profile_img":"https://i.pximg.net/user-profile/img/2023/09/14/15/22/23/24935616_66b7b300d99f8bf0955a48b8240cdff2_50.jpg","illust_content_type":{"sexual":0,"lo":false,"grotesque":false,"violent":false,"homosexual":false,"drug":false,"thoughts":false,"antisocial":false,"religion":false,"original":false,"furry":false,"bl":false,"yuri":false},"illust_series":false,"illust_id":147015426,"width":1700,"height":1198,"user_id":1599876,"rank":26,"yes_rank":44,"rating_count":91,"view_count":2310,"illust_upload_timestamp":1783609325,"attr":"","is_masked":false},{"title":"C108新刊ご予約開始♥","date":"2026年07月11日 17:00","tags":["女の子","創作百合","新刊サンプル","オリジナル500users入り"],"url":"https://i.pximg.net/c/480x960/img-master/img/2026/07/11/17/00/36/147074934_p0_master1200.jpg","illust_type":"0","illust_book_style":"0","illust_page_count":"9","user_name":"工藤える","profile_img":"https://i.pximg.net/user-profile/img/2023/02/03/18/28/18/23977148_c021285a510cb752d25791f90e33bc7b_50.jpg","illust_content_type":{"sexual":0,"lo":false,"grotesque":false,"violent":false,"homosexual":false,"drug":false,"thoughts":false,"antisocial":false,"religion":false,"original":true,"furry":false,"bl":false,"yuri":false},"illust_series":false,"illust_id":147074934,"width":928,"height":1310,"user_id":54891433,"rank":27,"yes_rank":0,"rating_count":480,"view_count":5381,"illust_upload_timestamp":1783756836,"attr":"original","is_masked":false},{"title":"ケーキの切れないセイカ","date":"2026年07月10日 20:55","tags":["漫画","LEGENDSZ-A","ガイセイ(pkmn)","セイカ(トレーナー)","ガイ(トレーナー)","ピュール","破れ鍋に綴じ蓋","適材適所"],"url":"https://i.pximg.net/c/480x960/img-master/img/2026/07/10/20/55/41/147042849_p0_master1200.jpg","illust_type":"1","illust_book_style":"0","illust_page_count":"10","user_name":"葵燐-kirin-","profile_img":"https://i.pximg.net/user-profile/img/2020/01/22/15/14/48/16889265_07ee0ebe17be1d80b625d02a49c32b36_50.jpg","illust_content_type":{"sexual":0,"lo":false,"grotesque":false,"violent":false,"homosexual":false,"drug":false,"thoughts":false,"antisocial":false,"religion":false,"original":false,"furry":false,"bl":false,"yuri":false},"illust_series":false,"illust_id":147042849,"width":1000,"height":1419,"user_id":8062876,"rank":28,"yes_rank":36,"rating_count":599,"view_count":17798,"illust_upload_timestamp":1783684541,"attr":"","is_masked":false},{"title":"-3.5-","date":"2026年07月11日 00:01","tags":["女の子","落書","鳴潮","秧秧玄翎","穂穂"],"url":"https://i.pximg.net/c/480x960/img-master/img/2026/07/11/00/01/50/147051939_p0_master1200.jpg","illust_type":"0","illust_book_style":"0","illust_page_count":"1","user_name":"超凶の狄璐卡","profile_img":"https://i.pximg.net/user-profile/img/2017/01/10/13/28/42/11988991_bae951a38d31d217fa1eceedc0aafdbe_50.jpg","illust_content_type":{"sexual":0,"lo":false,"grotesque":false,"violent":false,"homosexual":false,"drug":false,"thoughts":false,"antisocial":false,"religion":false,"original":false,"furry":false,"bl":false,"yuri":false},"illust_series":false,"illust_id":147051939,"width":4800,"height":2400,"user_id":22124330,"rank":29,"yes_rank":0,"rating_count":2695,"view_count":17595,"illust_upload_timestamp":1783695710,"attr":"","is_masked":false},{"title":"人の子などに惚れとうない 21","date":"2026年07月11日 00:02","tags":["漫画","妖狐","はよ結婚しろ","人の子などに惚れとうない","文明の利器","リアルビュー"],"url":"https://i.pximg.net/c/480x960/img-master/img/2026/07/11/00/02/29/147052009_p0_master1200.jpg","illust_type":"1","illust_book_style":"1","illust_page_count":"19","user_name":"小雨大豆 月歌の始まり連載中","profile_img":"https://i.pximg.net/user-profile/img/2011/01/04/15/48/37/2584657_e5029f6ca590e20f62f19e94696971fa_50.jpg","illust_content_type":{"sexual":0,"lo":false,"grotesque":false,"violent":false,"homosexual":false,"drug":false,"thoughts":false,"antisocial":false,"religion":false,"original":true,"furry":false,"bl":false,"yuri":false},"illust_series":{"illust_series_id":"333383","illust_series_user_id":"46393","illust_series_title":"人の子などに惚れとうない","illust_series_caption":"","illust_series_content_count":"21","illust_series_create_datetime":"2026-04-11 01:57:55","illust_series_content_illust_id":"147052009","illust_series_content_order":"21","page_url":"/user/46393/series/333383"},"illust_id":147052009,"width":1000,"height":1420,"user_id":46393,"rank":30,"yes_rank":0,"rating_count":949,"view_count":16206,"illust_upload_timestamp":1783695749,"attr":"original","is_masked":false},{"title":"リクエスト","date":"2026年07月10日 15:55","tags":["oc"],"url":"https://i.pximg.net/c/480x960/img-master/img/2026/07/10/15/55/36/147033141_p0_master1200.jpg","illust_type":"0","illust_book_style":"0","illust_page_count":"1","user_name":"COCOball","profile_img":"https://i.pximg.net/user-profile/img/2023/10/16/08/23/39/25053980_0c03a35f449f71ed83b855533e6f6a24_50.jpg","illust_content_type":{"sexual":0,"lo":false,"grotesque":false,"violent":false,"homosexual":false,"drug":false,"thoughts":false,"antisocial":false,"religion":false,"original":false,"furry":false,"bl":false,"yuri":false},"illust_series":false,"illust_id":147033141,"width":3858,"height":5826,"user_id":31383108,"rank":31,"yes_rank":77,"rating_count":296,"view_count":3801,"illust_upload_timestamp":1783666536,"attr":"","is_masked":false},{"title":"バスログ","date":"2026年07月11日 20:07","tags":["Limbus_Company"],"url":"https://i.pximg.net/c/480x960/img-master/img/2026/07/11/20/07/48/147081738_p0_master1200.jpg","illust_type":"0","illust_book_style":"0","illust_page_count":"106","user_name":"毎日面白いyeah","profile_img":"https://i.pximg.net/user-profile/img/2024/10/13/21/29/49/26473792_758182a9edd84756164b11c6ea3ad658_50.jpg","illust_content_type":{"sexual":0,"lo":false,"grotesque":false,"violent":false,"homosexual":false,"drug":false,"thoughts":false,"antisocial":false,"religion":false,"original":false,"furry":false,"bl":false,"yuri":false},"illust_series":false,"illust_id":147081738,"width":1409,"height":900,"user_id":110422946,"rank":32,"yes_rank":0,"rating_count":188,"view_count":3858,"illust_upload_timestamp":1783768068,"attr":"","is_masked":false},{"title":"哀ちゃんへの愛(映画マリオクッパ風に)","date":"2026年07月10日 00:21","tags":["漫画","灰原哀","落ち着け","狂気の沙汰","自爆","リクエスト作品","キチゲ解放","愛が重い","残念な変態"],"url":"https://i.pximg.net/c/480x960/img-master/img/2026/07/10/00/21/11/147016435_p0_master1200.jpg","illust_type":"1","illust_book_style":"0","illust_page_count":"5","user_name":"iPad Pro買ったR君","profile_img":"https://s.pximg.net/common/images/no_profile_s.png","illust_content_type":{"sexual":0,"lo":false,"grotesque":false,"violent":false,"homosexual":false,"drug":false,"thoughts":false,"antisocial":false,"religion":false,"original":false,"furry":false,"bl":false,"yuri":false},"illust_series":false,"illust_id":147016435,"width":4961,"height":7016,"user_id":75709706,"rank":33,"yes_rank":52,"rating_count":117,"view_count":34028,"illust_upload_timestamp":1783610471,"attr":"","is_masked":false},{"title":"人魚の歌の正体","date":"2026年07月10日 12:21","tags":["漫画","一命様お断り","人魚"],"url":"https://i.pximg.net/c/480x960/img-master/img/2026/07/10/12/21/01/147029284_p0_master1200.jpg","illust_type":"1","illust_book_style":"0","illust_page_count":"5","user_name":"窓口基","profile_img":"https://i.pximg.net/user-profile/img/2017/12/16/16/59/04/13568502_967df1853cf9ace087d8296a44837b0c_50.png","illust_content_type":{"sexual":0,"lo":false,"grotesque":false,"violent":false,"homosexual":false,"drug":false,"thoughts":false,"antisocial":false,"religion":false,"original":true,"furry":false,"bl":false,"yuri":false},"illust_series":{"illust_series_id":"259530","illust_series_user_id":"15033","illust_series_title":"一命様お断り","illust_series_caption":"ビームに載った漫画です。\r\n連載になりました。","illust_series_content_count":"12","illust_series_create_datetime":"2024-10-28 12:00:26","illust_series_content_illust_id":"147029284","illust_series_content_order":"11","page_url":"/user/15033/series/259530"},"illust_id":147029284,"width":643,"height":926,"user_id":15033,"rank":34,"yes_rank":62,"rating_count":189,"view_count":20782,"illust_upload_timestamp":1783653661,"attr":"original","is_masked":false},{"title":"무제","date":"2026年07月10日 19:45","tags":["おっぱい","ブルーアーカイブ","女先生(ブルーアーカイブ)","天地ニヤ","不知火カヤ","糸目","胸囲の格差社会"],"url":"https://i.pximg.net/c/480x960/img-master/img/2026/07/10/19/45/49/147039869_p0_master1200.jpg","illust_type":"0","illust_book_style":"0","illust_page_count":"1","user_name":"Xipa","profile_img":"https://i.pximg.net/user-profile/img/2025/09/08/03/19/39/27867082_b0320fe5a478b91021e6544cbd6dbaca_50.png","illust_content_type":{"sexual":0,"lo":false,"grotesque":false,"violent":false,"homosexual":false,"drug":false,"thoughts":false,"antisocial":false,"religion":false,"original":false,"furry":false,"bl":false,"yuri":false},"illust_series":false,"illust_id":147039869,"width":2900,"height":2900,"user_id":75450767,"rank":35,"yes_rank":54,"rating_count":1321,"view_count":25550,"illust_upload_timestamp":1783680349,"attr":"","is_masked":true},{"title":"💊💊💊","date":"2026年07月10日 14:19","tags":["レミエール・ダン","绝区零","ゼンレスゾーンゼロ","ゼンゼロ1000users入り"],"url":"https://i.pximg.net/c/480x960/img-master/img/2026/07/10/14/19/28/147031454_p0_master1200.jpg","illust_type":"0","illust_book_style":"0","illust_page_count":"1","user_name":"Coria","profile_img":"https://i.pximg.net/user-profile/img/2023/04/06/19/42/20/24258714_e158a7e061dc73a5d7c011857e433b9f_50.jpg","illust_content_type":{"sexual":1,"lo":false,"grotesque":false,"violent":false,"homosexual":false,"drug":false,"thoughts":false,"antisocial":false,"religion":false,"original":false,"furry":false,"bl":false,"yuri":false},"illust_series":false,"illust_id":147031454,"width":4610,"height":8821,"user_id":27848445,"rank":36,"yes_rank":101,"rating_count":408,"view_count":3448,"illust_upload_timestamp":1783660768,"attr":"","is_masked":true},{"title":"Tempest","date":"2026年07月11日 01:57","tags":["提丰","明日方舟:终末地","明日方舟","我猜可能叫阵风(?)","アークナイツ"],"url":"https://i.pximg.net/c/480x960/img-master/img/2026/07/11/01/57/48/147055921_p0_master1200.jpg","illust_type":"0","illust_book_style":"0","illust_page_count":"1","user_name":"Whate=3r","profile_img":"https://i.pximg.net/user-profile/img/2025/04/04/10/21/20/27190097_fcd54f853f46d49f9740a599870b271e_50.jpg","illust_content_type":{"sexual":0,"lo":false,"grotesque":false,"violent":false,"homosexual":false,"drug":false,"thoughts":false,"antisocial":false,"religion":false,"original":false,"furry":false,"bl":false,"yuri":false},"illust_series":false,"illust_id":147055921,"width":2048,"height":2732,"user_id":12982882,"rank":37,"yes_rank":0,"rating_count":1555,"view_count":20568,"illust_upload_timestamp":1783702668,"attr":"","is_masked":false},{"title":"シンデレラ Black","date":"2026年07月10日 00:04","tags":["勝利の女神:NIKKE","シンデレラ(勝利の女神:NIKKE)","グレイブ(勝利の女神:NIKKE)","シンデレラ:クリスタルウェーブ","おっぱい","水着"],"url":"https://i.pximg.net/c/480x960/img-master/img/2026/07/10/00/04/17/147015614_p0_master1200.jpg","illust_type":"0","illust_book_style":"0","illust_page_count":"1","user_name":"RUHEE ルヒ","profile_img":"https://i.pximg.net/user-profile/img/2024/02/02/22/56/36/25468000_027e0f2c95e0897069199199780da450_50.png","illust_content_type":{"sexual":1,"lo":false,"grotesque":false,"violent":false,"homosexual":false,"drug":false,"thoughts":false,"antisocial":false,"religion":false,"original":false,"furry":false,"bl":false,"yuri":false},"illust_series":false,"illust_id":147015614,"width":1500,"height":2528,"user_id":1213814,"rank":38,"yes_rank":66,"rating_count":602,"view_count":13371,"illust_upload_timestamp":1783609457,"attr":"","is_masked":true},{"title":"SCPをざっくり紹介358","date":"2026年07月11日 21:00","tags":["漫画","SCP","SCPをざっくり紹介","SCP_Foundation","ツクテーン!","SCP-8919","ﾂｸﾃｰﾝ","ちょっと黙れお前","サンズ"],"url":"https://i.pximg.net/c/480x960/img-master/img/2026/07/12/10/09/35/147084023_p0_master1200.jpg","illust_type":"1","illust_book_style":"0","illust_page_count":"5","user_name":"松(A・TYPEcorp.)","profile_img":"https://i.pximg.net/user-profile/img/2013/09/02/21/17/21/6765257_c216d5314027040a073ba61f0add6dea_50.png","illust_content_type":{"sexual":0,"lo":false,"grotesque":false,"violent":false,"homosexual":false,"drug":false,"thoughts":false,"antisocial":false,"religion":false,"original":false,"furry":false,"bl":false,"yuri":false},"illust_series":{"illust_series_id":"10631","illust_series_user_id":"18923","illust_series_title":"SCPをざっくり紹介","illust_series_caption":"\n\nSCPとは海外の怪奇創作をまとめたサイトの通称で、\nSCP財団という世界規模の架空の団体が確保、収容、保護した、SCPと呼ばれる物や生物、場所などの報告をまとめたレポートという体で創作してます。","illust_series_content_count":"358","illust_series_create_datetime":"2017-07-03 16:12:11","illust_series_content_illust_id":"147084023","illust_series_content_order":"358","page_url":"/user/18923/series/10631"},"illust_id":147084023,"width":777,"height":1090,"user_id":18923,"rank":39,"yes_rank":0,"rating_count":447,"view_count":12646,"illust_upload_timestamp":1783818575,"attr":"","is_masked":false},{"title":"運動部エリア","date":"2026年07月10日 00:00","tags":["Fate/GrandOrder","FGO","坂田金時(Fate)","アンドロメダ(Fate)","プトレマイオス(Fate)","アルトリア・キャスター","FGOご本人"],"url":"https://i.pximg.net/c/480x960/img-master/img/2026/07/10/00/00/26/147015151_p0_master1200.jpg","illust_type":"0","illust_book_style":"0","illust_page_count":"1","user_name":"煮たか","profile_img":"https://i.pximg.net/user-profile/img/2025/02/02/01/46/57/26918761_efc85e137182fbb1cd83eab2bfd00719_50.jpg","illust_content_type":{"sexual":0,"lo":false,"grotesque":false,"violent":false,"homosexual":false,"drug":false,"thoughts":false,"antisocial":false,"religion":false,"original":false,"furry":false,"bl":false,"yuri":false},"illust_series":false,"illust_id":147015151,"width":875,"height":619,"user_id":289725,"rank":40,"yes_rank":49,"rating_count":122,"view_count":5592,"illust_upload_timestamp":1783609226,"attr":"","is_masked":false},{"title":"ユリ","date":"2026年07月10日 21:25","tags":["オリジナル","創作"],"url":"https://i.pximg.net/c/480x960/img-master/img/2026/07/10/21/25/55/147044406_p0_master1200.jpg","illust_type":"0","illust_book_style":"0","illust_page_count":"1","user_name":"やぎ","profile_img":"https://i.pximg.net/user-profile/img/2021/05/08/03/44/52/20663408_9dd0161823e3475589b929a9a2cbe5b1_50.jpg","illust_content_type":{"sexual":0,"lo":false,"grotesque":false,"violent":false,"homosexual":false,"drug":false,"thoughts":false,"antisocial":false,"religion":false,"original":true,"furry":false,"bl":false,"yuri":false},"illust_series":false,"illust_id":147044406,"width":1460,"height":2032,"user_id":39583320,"rank":41,"yes_rank":240,"rating_count":197,"view_count":1322,"illust_upload_timestamp":1783686355,"attr":"original","is_masked":false},{"title":"デートの終盤","date":"2026年07月10日 10:36","tags":["漫画","酒寄彩葉","超かぐや姫!","超かぐや姫","ヤチいろ","超かぐや姫!1000users入り"],"url":"https://i.pximg.net/c/480x960/img-master/img/2026/07/10/10/36/41/147027337_p0_master1200.jpg","illust_type":"1","illust_book_style":"0","illust_page_count":"1","user_name":"T0nyS","profile_img":"https://i.pximg.net/user-profile/img/2023/12/31/17/39/44/25334006_2ad7043cd562b6d4672a5289dd61331a_50.jpg","illust_content_type":{"sexual":0,"lo":false,"grotesque":false,"violent":false,"homosexual":false,"drug":false,"thoughts":false,"antisocial":false,"religion":false,"original":true,"furry":false,"bl":false,"yuri":false},"illust_series":{"illust_series_id":"325575","illust_series_user_id":"65407506","illust_series_title":"超かぐや姫！","illust_series_caption":"","illust_series_content_count":"47","illust_series_create_datetime":"2026-02-18 04:21:49","illust_series_content_illust_id":"147027337","illust_series_content_order":"46","page_url":"/user/65407506/series/325575"},"illust_id":147027337,"width":2480,"height":3508,"user_id":65407506,"rank":42,"yes_rank":123,"rating_count":188,"view_count":4408,"illust_upload_timestamp":1783647401,"attr":"original","is_masked":false},{"title":"蒼が過ぎ去った跡","date":"2026年07月11日 00:00","tags":["オリジナル","風景","背景","女の子","イラスト","夏","創作"],"url":"https://i.pximg.net/c/480x960/img-master/img/2026/07/11/00/00/33/147051727_p0_master1200.jpg","illust_type":"0","illust_book_style":"0","illust_page_count":"2","user_name":"banishment","profile_img":"https://i.pximg.net/user-profile/img/2020/08/16/14/42/45/19191489_09b741684435ca2a06c06a3779821948_50.png","illust_content_type":{"sexual":0,"lo":false,"grotesque":false,"violent":false,"homosexual":false,"drug":false,"thoughts":false,"antisocial":false,"religion":false,"original":true,"furry":false,"bl":false,"yuri":false},"illust_series":false,"illust_id":147051727,"width":4000,"height":2251,"user_id":23223750,"rank":43,"yes_rank":0,"rating_count":616,"view_count":6361,"illust_upload_timestamp":1783695633,"attr":"original","is_masked":false},{"title":"月下香幽芳","date":"2026年07月11日 00:00","tags":["女の子","少女","vtuber"],"url":"https://i.pximg.net/c/480x960/img-master/img/2026/07/11/00/00/14/147051624_p0_master1200.jpg","illust_type":"0","illust_book_style":"0","illust_page_count":"1","user_name":"Say HANa","profile_img":"https://i.pximg.net/user-profile/img/2020/11/10/18/01/26/19648130_851f256b592686a9d4585a0e90a412b7_50.png","illust_content_type":{"sexual":0,"lo":false,"grotesque":false,"violent":false,"homosexual":false,"drug":false,"thoughts":false,"antisocial":false,"religion":false,"original":true,"furry":false,"bl":false,"yuri":false},"illust_series":false,"illust_id":147051624,"width":1190,"height":805,"user_id":1443093,"rank":44,"yes_rank":0,"rating_count":317,"view_count":2802,"illust_upload_timestamp":1783695614,"attr":"original","is_masked":false},{"title":"no title","date":"2026年07月10日 22:44","tags":["美少女","可愛い","イラスト","女の子","鹿目まどか","魔法少女","魔法少女まどか","魔法少女まどかマギカ","魔法少女まどか☆マギカ","まどか☆マギカ500users入り"],"url":"https://i.pximg.net/c/480x960/img-master/img/2026/07/10/22/44/14/147048187_p0_master1200.jpg","illust_type":"0","illust_book_style":"0","illust_page_count":"1","user_name":"飞机云君","profile_img":"https://i.pximg.net/user-profile/img/2022/04/18/13/20/23/22569072_14eac5b8916468ae73ef242369c67ce9_50.jpg","illust_content_type":{"sexual":0,"lo":false,"grotesque":false,"violent":false,"homosexual":false,"drug":false,"thoughts":false,"antisocial":false,"religion":false,"original":false,"furry":false,"bl":false,"yuri":false},"illust_series":false,"illust_id":147048187,"width":3508,"height":2480,"user_id":80688950,"rank":45,"yes_rank":112,"rating_count":283,"view_count":1442,"illust_upload_timestamp":1783691054,"attr":"","is_masked":false},{"title":"「水着、楽しみにしててくださいね 先輩♡」","date":"2026年07月10日 18:31","tags":["女の子","オリジナル","自撮り","後輩ちゃん","マイクロビキニ","はいてない"],"url":"https://i.pximg.net/c/480x960/img-master/img/2026/07/10/18/31/14/147037302_p0_master1200.jpg","illust_type":"0","illust_book_style":"0","illust_page_count":"1","user_name":"むにんしき","profile_img":"https://i.pximg.net/user-profile/img/2022/01/23/14/48/44/22097855_a3d7098b85e8ebb243489004a852322e_50.png","illust_content_type":{"sexual":1,"lo":false,"grotesque":false,"violent":false,"homosexual":false,"drug":false,"thoughts":false,"antisocial":false,"religion":false,"original":true,"furry":false,"bl":false,"yuri":false},"illust_series":false,"illust_id":147037302,"width":868,"height":1228,"user_id":67442991,"rank":46,"yes_rank":144,"rating_count":1294,"view_count":16323,"illust_upload_timestamp":1783675874,"attr":"original","is_masked":true},{"title":"ちびカエ　其の漆","date":"2026年07月11日 13:15","tags":["鬼滅の刃","胡蝶カナエ","胡蝶しのぶ","ちびカエしの","栗花落カナヲ","甘露寺蜜璃","嘴平伊之助","鬼滅の刃100users入り"],"url":"https://i.pximg.net/c/480x960/img-master/img/2026/07/11/13/15/07/147069053_p0_master1200.jpg","illust_type":"0","illust_book_style":"0","illust_page_count":"10","user_name":"園れもん","profile_img":"https://i.pximg.net/user-profile/img/2021/05/02/18/10/40/20629285_e0a1b227950d347d721d201254ea8079_50.jpg","illust_content_type":{"sexual":0,"lo":false,"grotesque":false,"violent":false,"homosexual":false,"drug":false,"thoughts":false,"antisocial":false,"religion":false,"original":false,"furry":false,"bl":false,"yuri":false},"illust_series":false,"illust_id":147069053,"width":2894,"height":4093,"user_id":28159846,"rank":47,"yes_rank":0,"rating_count":267,"view_count":2915,"illust_upload_timestamp":1783743307,"attr":"","is_masked":false},{"title":"定食屋さんのギャル店員と忍者さん","date":"2026年07月10日 20:57","tags":["漫画","創作","オリジナル","筋肉","忍者","ギャル"],"url":"https://i.pximg.net/c/480x960/img-master/img/2026/07/10/20/57/55/147042924_p0_master1200.jpg","illust_type":"1","illust_book_style":"0","illust_page_count":"4","user_name":"りん次郎","profile_img":"https://i.pximg.net/user-profile/img/2017/05/14/15/38/43/12557313_e753b448836ad4c91400188bf13a40c4_50.png","illust_content_type":{"sexual":0,"lo":false,"grotesque":false,"violent":false,"homosexual":false,"drug":false,"thoughts":false,"antisocial":false,"religion":false,"original":true,"furry":false,"bl":false,"yuri":false},"illust_series":{"illust_series_id":"333348","illust_series_user_id":"24778357","illust_series_title":"忍者さん漫画シリーズ（単話）","illust_series_caption":"１話ずつ読みたい方向けのシリーズです。\r\n甘いものが好きなムキムキの忍者さんが困っている人を助けたり、みんなで美味しいものを食べたりします。","illust_series_content_count":"24","illust_series_create_datetime":"2026-04-10 23:12:30","illust_series_content_illust_id":"147042924","illust_series_content_order":"24","page_url":"/user/24778357/series/333348"},"illust_id":147042924,"width":900,"height":1200,"user_id":24778357,"rank":48,"yes_rank":59,"rating_count":634,"view_count":18051,"illust_upload_timestamp":1783684675,"attr":"original","is_masked":false},{"title":"「小さくて可愛い文芸部の知的な先輩」4話前編更新されました","date":"2026年07月10日 12:00","tags":["漫画","コミックNewtype","ラブコメ","甘露アメの合法な方","うたた寝"],"url":"https://i.pximg.net/c/480x960/img-master/img/2026/07/10/12/00/34/147028793_p0_master1200.jpg","illust_type":"1","illust_book_style":"0","illust_page_count":"5","user_name":"あめこ/甘露アメ","profile_img":"https://i.pximg.net/user-profile/img/2012/12/04/09/22/27/5495659_b48178a743210c4cbf81c938f267752d_50.jpg","illust_content_type":{"sexual":0,"lo":false,"grotesque":false,"violent":false,"homosexual":false,"drug":false,"thoughts":false,"antisocial":false,"religion":false,"original":true,"furry":false,"bl":false,"yuri":false},"illust_series":{"illust_series_id":"345498","illust_series_user_id":"42039","illust_series_title":"ちい乗せ","illust_series_caption":"","illust_series_content_count":"6","illust_series_create_datetime":"2026-06-29 03:27:51","illust_series_content_illust_id":"147028793","illust_series_content_order":"6","page_url":"/user/42039/series/345498"},"illust_id":147028793,"width":1000,"height":1435,"user_id":42039,"rank":49,"yes_rank":395,"rating_count":195,"view_count":28688,"illust_upload_timestamp":1783652434,"attr":"original","is_masked":false},{"title":"水着シロコ","date":"2026年07月10日 00:55","tags":["砂狼シロコ","ブルーアーカイブ","ブルアカ","BlueArchive","シロコ(ブルーアーカイブ)","競泳水着","水着シロコ"],"url":"https://i.pximg.net/c/480x960/img-master/img/2026/07/10/00/55/46/147017636_p0_master1200.jpg","illust_type":"0","illust_book_style":"0","illust_page_count":"1","user_name":"泉水茜","profile_img":"https://i.pximg.net/user-profile/img/2016/04/23/16/45/50/10839422_26d9927e4effba0c609f94767b910e24_50.png","illust_content_type":{"sexual":0,"lo":false,"grotesque":false,"violent":false,"homosexual":false,"drug":false,"thoughts":false,"antisocial":false,"religion":false,"original":false,"furry":false,"bl":false,"yuri":false},"illust_series":false,"illust_id":147017636,"width":531,"height":754,"user_id":786736,"rank":50,"yes_rank":419,"rating_count":93,"view_count":3229,"illust_upload_timestamp":1783612546,"attr":"","is_masked":false}],"mode":"daily","content":"all","page":1,"prev":false,"next":2,"date":"20260711","prev_date":"20260710","next_date":false,"rank_total":500,"meta":{"h_title":"[pixiv] Overall Daily Rankings 7/11/2026","meta_ogp":{"description":"Check out the Overall Daily Rankings!","image":"","title":"[2026.07.11] Overall Daily Rankings"},"twitter_card":{"card":"summary_large_image","site":"@pixiv","description":"Check out the Overall Daily Rankings!","image":"","title":"[2026.07.11] Overall Daily Rankings"},"h_canonical":"https://www.pixiv.net/ranking.php?mode=daily&date=20260711","title":"Overall Daily Rankings"},"date_range_text":"7/11/2026","zoneConfig":{"header":{"url":"https://pixon.ads-pixiv.net/show?zone_id=header&format=js&s=0&up=0&ng=g&l=en&uri=%2Franking.php&ref=www.pixiv.net%2Franking.php%3Fformat%3Djson%26mode%3Ddaily&D=21ccb671d931faa&ab_test_digits_first=94&yuid=VJUmcVA&num=6a53340415"},"footer":{"url":"https://pixon.ads-pixiv.net/show?zone_id=footer&format=js&s=0&up=0&ng=g&l=en&uri=%2Franking.php&ref=www.pixiv.net%2Franking.php%3Fformat%3Djson%26mode%3Ddaily&D=21ccb671d931faa&ab_test_digits_first=94&yuid=VJUmcVA&num=6a533404470"},"logo":{"url":"https://pixon.ads-pixiv.net/show?zone_id=logo_side&format=js&s=0&up=0&ng=g&l=en&uri=%2Franking.php&ref=www.pixiv.net%2Franking.php%3Fformat%3Djson%26mode%3Ddaily&D=21ccb671d931faa&ab_test_digits_first=94&yuid=VJUmcVA&num=6a53340454"},"ad_logo":{"url":"https://pixon.ads-pixiv.net/show?zone_id=t_logo_side&format=js&s=0&up=0&ng=g&l=en&os=and&uri=%2Franking.php&ref=www.pixiv.net%2Franking.php%3Fformat%3Djson%26mode%3Ddaily&D=21ccb671d931faa&ab_test_digits_first=94&yuid=VJUmcVA&num=6a533404345"}}}